Compiled from "T01_WhatIsThread.java"
public class T01_WhatIsThread$MyThread extends java.lang.Thread {
  public T01_WhatIsThread$MyThread();
    Code:
       0: aload_0
       1: invokespecial #1                  // Method java/lang/Thread."<init>":()V
       4: return

  public void run();
    Code:
       0: iconst_0
       1: istore_1
       2: iload_1
       3: bipush        10
       5: if_icmpge     37
       8: getstatic     #2                  // Field java/lang/System.out:Ljava/io/PrintStream;
      11: ldc           #3                  // String MyThread
      13: invokevirtual #4                  // Method java/io/PrintStream.println:(Ljava/lang/String;)V
      16: getstatic     #5                  // Field java/util/concurrent/TimeUnit.MILLISECONDS:Ljava/util/concurrent/TimeUnit;
      19: lconst_1
      20: invokevirtual #6                  // Method java/util/concurrent/TimeUnit.sleep:(J)V
      23: goto          31
      26: astore_2
      27: aload_2
      28: invokevirtual #8                  // Method java/lang/InterruptedException.printStackTrace:()V
      31: iinc          1, 1
      34: goto          2
      37: return
    Exception table:
       from    to  target type
          16    23    26   Class java/lang/InterruptedException
}
